mexm/__init__.py
mexm/elements.py
mexm/exception.py
mexm/util.py
mexm-0.1.0.dist-info/LICENSE
mexm-0.1.0.dist-info/METADATA
mexm-0.1.0.dist-info/WHEEL
mexm-0.1.0.dist-info/top_level.txt
mexm-0.1.0.dist-info/zip-safe
mexm-0.1.0.dist-info/RECORD
