Metadata-Version: 2.1
Name: mexm
Version: 0.1.0
Summary: Materials Ex Machina
Home-page: https://github.com/eragasa/mexm-base
Author: Eugene J. Ragasa
Author-email: eragasa@osc.edu
License: MIT License
Platform: UNKNOWN
